hexdump2/VERSION
hexdump2/__init__.py
hexdump2/__main__.py
hexdump2/hexdump2.py
hexdump2-1.2.2.dist-info/LICENSE
hexdump2-1.2.2.dist-info/METADATA
hexdump2-1.2.2.dist-info/WHEEL
hexdump2-1.2.2.dist-info/entry_points.txt
hexdump2-1.2.2.dist-info/top_level.txt
hexdump2-1.2.2.dist-info/RECORD
