Metadata-Version: 2.1
Name: hexdump2
Version: 1.2.2
Summary: An imperfect replica of hexdump -C
Home-page: https://github.com/HGrooms/hexdump2
Author: Hiss Grooms
Author-email: hiss.grooms0q@icloud.com
License: MIT
Project-URL: Source, https://github.com/HGrooms/hexdump2
Project-URL: Issues, https://github.com/HGrooms/hexdump2/issues
Project-URL: Changelog, https://github.com/HGrooms/hexdump2/blob/master/CHANGELOG.md
Classifier: Programming Language :: Python :: 3
Classifier: License :: OSI Approved :: MIT License
Requires-Python: >=3.6
License-File: LICENSE
Requires-Dist: colorama
Requires-Dist: importlib-metadata ; python_version < "3.8"
Provides-Extra: dev
Requires-Dist: pre-commit ; extra == 'dev'
Requires-Dist: black ; extra == 'dev'
Requires-Dist: pylint ; extra == 'dev'
